{"meta":{"chat":{"id":374009868,"first_name":"Volodymyr","last_name":"Boiko","username":"angrybaget","type":"private"},"user":{"id":374009868,"first_name":"Volodymyr","last_name":"Boiko","username":"angrybaget"},"sessionId":374009868,"current":"end","from":{"id":374009868,"first_name":"Volodymyr","last_name":"Boiko","username":"angrybaget"}},"data":{},"backHistory":{},"backHistoryArgs":{},"invokeArgs":[],"keyboardMap":{"bad2":{"value":"bad"},"good":{"value":"good"},"send":{"value":"send"},"back":{"go":"start"}}}